confluent_schema_registry_client
