Metadata-Version: 1.0
Name: confluent-schema-registry-client
Version: 1.1.0
Summary: A simple client Confluent's Avro Schema Registry
Home-page: http://github.com/gamechanger/confluent_schema_registry_client
Author: Tom Leach
Author-email: tom@gc.com
License: MIT
Keywords: confluent schema registry client avro http rest
Platform: UNKNOWN
